verysimplemodulevis/__init__.py
verysimplemodulevis/__init___.py
verysimplemodulevis/mymodule.py
verysimplemodulevis-0.0.53.dist-info/LICENSE
verysimplemodulevis-0.0.53.dist-info/METADATA
verysimplemodulevis-0.0.53.dist-info/WHEEL
verysimplemodulevis-0.0.53.dist-info/top_level.txt
verysimplemodulevis-0.0.53.dist-info/RECORD
