Metadata-Version: 2.1
Name: verysimplemodulevis
Version: 0.0.53
Summary: Meu primeiro projeto em Python
Author: Victor Macedo
Author-email: victormacedocarvalho09@gmail.com
License: MIT
License-File: LICENSE
